amundsen_application/__init__.py
amundsen_application/config.py
amundsen_application/deprecations.py
amundsen_application/oidc_config.py
amundsen_application/wsgi.py
amundsen_application/api/__init__.py
amundsen_application/api/exceptions.py
amundsen_application/api/v0.py
amundsen_application/api/announcements/__init__.py
amundsen_application/api/announcements/v0.py
amundsen_application/api/issue/__init__.py
amundsen_application/api/issue/issue.py
amundsen_application/api/log/__init__.py
amundsen_application/api/log/v0.py
amundsen_application/api/mail/__init__.py
amundsen_application/api/mail/v0.py
amundsen_application/api/metadata/__init__.py
amundsen_application/api/metadata/v0.py
amundsen_application/api/notice/__init__.py
amundsen_application/api/notice/v0.py
amundsen_application/api/preview/__init__.py
amundsen_application/api/preview/v0.py
amundsen_application/api/preview/dashboard/__init__.py
amundsen_application/api/preview/dashboard/v0.py
amundsen_application/api/preview/dashboard/dashboard_preview/__init__.py
amundsen_application/api/preview/dashboard/dashboard_preview/mode_preview.py
amundsen_application/api/preview/dashboard/dashboard_preview/preview_factory_method.py
amundsen_application/api/quality/__init__.py
amundsen_application/api/quality/v0.py
amundsen_application/api/search/__init__.py
amundsen_application/api/search/v1.py
amundsen_application/api/utils/__init__.py
amundsen_application/api/utils/metadata_utils.py
amundsen_application/api/utils/notification_utils.py
amundsen_application/api/utils/request_utils.py
amundsen_application/api/utils/response_utils.py
amundsen_application/api/utils/search_utils.py
amundsen_application/base/__init__.py
amundsen_application/base/base_announcement_client.py
amundsen_application/base/base_bigquery_preview_client.py
amundsen_application/base/base_issue_tracker_client.py
amundsen_application/base/base_mail_client.py
amundsen_application/base/base_notice_client.py
amundsen_application/base/base_preview.py
amundsen_frontend-4.3.0.dist-info/LICENSE
amundsen_frontend-4.3.0.dist-info/METADATA
amundsen_frontend-4.3.0.dist-info/NOTICE
amundsen_frontend-4.3.0.dist-info/WHEEL
amundsen_frontend-4.3.0.dist-info/entry_points.txt
amundsen_frontend-4.3.0.dist-info/top_level.txt
amundsen_frontend-4.3.0.dist-info/RECORD
