Metadata-Version: 2.1
Name: amundsen-frontend
Version: 4.3.0
Summary: Web UI for Amundsen
Home-page: https://www.github.com/amundsen-io/amundsen/tree/main/frontend
Maintainer: Amundsen TSC
Maintainer-email: amundsen-tsc@lists.lfai.foundation
License: UNKNOWN
Platform: UNKNOWN
Classifier: Programming Language :: Python :: 3.8
Classifier: Programming Language :: Python :: 3.9
Requires-Python: >=3.8
Requires-Dist: responses ==0.12.1
Requires-Dist: SQLAlchemy ==1.3.23
Requires-Dist: retrying <2.0,>=1.3.3
Requires-Dist: amundsen-common >=0.27.0
Requires-Dist: attrs >=19.1.0
Requires-Dist: boto3 ==1.17.23
Requires-Dist: click ==8.1.7
Requires-Dist: flasgger ==0.9.5
Requires-Dist: Flask ==2.2.5
Requires-Dist: Flask-RESTful >=0.3.9
Requires-Dist: flask-cors ==3.0.10
Requires-Dist: itsdangerous ==2.1.2
Requires-Dist: Jinja2 ==3.1.2
Requires-Dist: jsonschema <4.0,>=3.0.1
Requires-Dist: marshmallow <=3.6,>=3.0
Requires-Dist: marshmallow3-annotations >=1.1.0
Requires-Dist: pytz ==2021.1
Requires-Dist: requests >=2.25.0
Requires-Dist: requests-aws4auth ==1.1.0
Requires-Dist: statsd ==3.2.1
Requires-Dist: typing ==3.6.4
Requires-Dist: werkzeug ==3.0.1
Requires-Dist: wheel ==0.38.1
Requires-Dist: dataclasses ==0.8 ; python_version < "3.7"
Provides-Extra: all
Requires-Dist: responses ==0.12.1 ; extra == 'all'
Requires-Dist: SQLAlchemy ==1.3.23 ; extra == 'all'
Requires-Dist: retrying <2.0,>=1.3.3 ; extra == 'all'
Requires-Dist: amundsen-common >=0.27.0 ; extra == 'all'
Requires-Dist: attrs >=19.1.0 ; extra == 'all'
Requires-Dist: boto3 ==1.17.23 ; extra == 'all'
Requires-Dist: click ==8.1.7 ; extra == 'all'
Requires-Dist: flasgger ==0.9.5 ; extra == 'all'
Requires-Dist: Flask ==2.2.5 ; extra == 'all'
Requires-Dist: Flask-RESTful >=0.3.9 ; extra == 'all'
Requires-Dist: flask-cors ==3.0.10 ; extra == 'all'
Requires-Dist: itsdangerous ==2.1.2 ; extra == 'all'
Requires-Dist: Jinja2 ==3.1.2 ; extra == 'all'
Requires-Dist: jsonschema <4.0,>=3.0.1 ; extra == 'all'
Requires-Dist: marshmallow <=3.6,>=3.0 ; extra == 'all'
Requires-Dist: marshmallow3-annotations >=1.1.0 ; extra == 'all'
Requires-Dist: pytz ==2021.1 ; extra == 'all'
Requires-Dist: requests >=2.25.0 ; extra == 'all'
Requires-Dist: requests-aws4auth ==1.1.0 ; extra == 'all'
Requires-Dist: statsd ==3.2.1 ; extra == 'all'
Requires-Dist: typing ==3.6.4 ; extra == 'all'
Requires-Dist: werkzeug ==3.0.1 ; extra == 'all'
Requires-Dist: wheel ==0.38.1 ; extra == 'all'
Requires-Dist: flake8 >=3.9.2 ; extra == 'all'
Requires-Dist: flake8-tidy-imports >=4.3.0 ; extra == 'all'
Requires-Dist: isort[colors] ~=5.8.0 ; extra == 'all'
Requires-Dist: mock >=4.0.3 ; extra == 'all'
Requires-Dist: mypy <0.900,>=0.812 ; extra == 'all'
Requires-Dist: pytest >=6.2.4 ; extra == 'all'
Requires-Dist: pytest-cov >=2.12.0 ; extra == 'all'
Requires-Dist: pytest-env >=0.6.2 ; extra == 'all'
Requires-Dist: pytest-mock >=3.6.1 ; extra == 'all'
Requires-Dist: typed-ast >=1.4.3 ; extra == 'all'
Requires-Dist: pyspark ==3.0.1 ; extra == 'all'
Requires-Dist: flaskoidc >=1.0.0 ; extra == 'all'
Requires-Dist: pyarrow ==3.0.0 ; extra == 'all'
Requires-Dist: google-cloud-bigquery <3.0.0,>=2.13.1 ; extra == 'all'
Requires-Dist: flatten-dict ==0.3.0 ; extra == 'all'
Requires-Dist: jira ==3.0.1 ; extra == 'all'
Requires-Dist: asana ==0.10.3 ; extra == 'all'
Requires-Dist: dataclasses ==0.8 ; (python_version < "3.7") and extra == 'all'
Provides-Extra: asana
Requires-Dist: asana ==0.10.3 ; extra == 'asana'
Provides-Extra: bigquery_preview
Requires-Dist: google-cloud-bigquery <3.0.0,>=2.13.1 ; extra == 'bigquery_preview'
Requires-Dist: flatten-dict ==0.3.0 ; extra == 'bigquery_preview'
Provides-Extra: dev
Requires-Dist: flake8 >=3.9.2 ; extra == 'dev'
Requires-Dist: flake8-tidy-imports >=4.3.0 ; extra == 'dev'
Requires-Dist: isort[colors] ~=5.8.0 ; extra == 'dev'
Requires-Dist: mock >=4.0.3 ; extra == 'dev'
Requires-Dist: mypy <0.900,>=0.812 ; extra == 'dev'
Requires-Dist: pytest >=6.2.4 ; extra == 'dev'
Requires-Dist: pytest-cov >=2.12.0 ; extra == 'dev'
Requires-Dist: pytest-env >=0.6.2 ; extra == 'dev'
Requires-Dist: pytest-mock >=3.6.1 ; extra == 'dev'
Requires-Dist: typed-ast >=1.4.3 ; extra == 'dev'
Requires-Dist: pyspark ==3.0.1 ; extra == 'dev'
Provides-Extra: jira
Requires-Dist: jira ==3.0.1 ; extra == 'jira'
Provides-Extra: oidc
Requires-Dist: flaskoidc >=1.0.0 ; extra == 'oidc'
Provides-Extra: pyarrow
Requires-Dist: pyarrow ==3.0.0 ; extra == 'pyarrow'
